odoo10_addon_product_dimension-10.0.1.0.0.99.dev5-nspkg.pth
odoo/addons/product_dimension/README.rst
odoo/addons/product_dimension/__init__.py
odoo/addons/product_dimension/__manifest__.py
odoo/addons/product_dimension/i18n/fi.po
odoo/addons/product_dimension/i18n/product_dimension.pot
odoo/addons/product_dimension/models/__init__.py
odoo/addons/product_dimension/models/product.py
odoo/addons/product_dimension/static/description/icon.png
odoo/addons/product_dimension/tests/__init__.py
odoo/addons/product_dimension/tests/test_compute_volume.py
odoo/addons/product_dimension/views/product_view.xml
odoo10_addon_product_dimension-10.0.1.0.0.99.dev5.dist-info/METADATA
odoo10_addon_product_dimension-10.0.1.0.0.99.dev5.dist-info/WHEEL
odoo10_addon_product_dimension-10.0.1.0.0.99.dev5.dist-info/namespace_packages.txt
odoo10_addon_product_dimension-10.0.1.0.0.99.dev5.dist-info/top_level.txt
odoo10_addon_product_dimension-10.0.1.0.0.99.dev5.dist-info/RECORD
