Metadata-Version: 2.1
Name: odoo10-addon-product-dimension
Version: 10.0.1.0.0.99.dev5
Summary: Product Dimension
Home-page: UNKNOWN
Author: ADHOC SA, Camptocamp, Odoo Community Association (OCA)
Author-email: support@odoo-community.org
License: AGPL-3
Platform: UNKNOWN
Classifier: Programming Language :: Python
Classifier: Framework :: Odoo
Classifier: License :: OSI Approved :: GNU Affero General Public License v3
Requires-Python: ~=2.7
Requires-Dist: odoo (<10.1dev,>=10.0)
